long2short/__init__.py
long2short/chunker.py
long2short/long2short.py
long2short/models.py
long2short/tokenizer.py
long2short-0.1.4.dist-info/METADATA
long2short-0.1.4.dist-info/WHEEL
long2short-0.1.4.dist-info/top_level.txt
long2short-0.1.4.dist-info/RECORD
