Metadata-Version: 2.2
Name: long2short
Version: 0.1.4
Summary: A flexible text summarization library to summarize long documents supporting multiple LLM providers
Author-email: Mohammed Arshad <mdarshad1000@gmail.com>
Keywords: summarization,text-processing,llms,openai,anthropic
Classifier: Development Status :: 3 - Alpha
Classifier: Intended Audience :: Developers
Classifier: Programming Language :: Python :: 3
Classifier: Programming Language :: Python :: 3.8
Classifier: Programming Language :: Python :: 3.9
Classifier: Programming Language :: Python :: 3.10
Classifier: Programming Language :: Python :: 3.11
Requires-Python: >=3.8
Requires-Dist: openai>=1.0.0
Requires-Dist: anthropic>=0.3.0
Requires-Dist: tiktoken>=0.5.0
Requires-Dist: tqdm>=4.65.0
